streamlit_cytoscapejs/__init__.py
streamlit_cytoscapejs/frontend/build/asset-manifest.json
streamlit_cytoscapejs/frontend/build/bootstrap.min.css
streamlit_cytoscapejs/frontend/build/index.html
streamlit_cytoscapejs/frontend/build/precache-manifest.0f9784b7513a9f54198051f6ae173c37.js
streamlit_cytoscapejs/frontend/build/service-worker.js
streamlit_cytoscapejs/frontend/build/static/js/2.ab48aa38.chunk.js
streamlit_cytoscapejs/frontend/build/static/js/2.ab48aa38.chunk.js.LICENSE.txt
streamlit_cytoscapejs/frontend/build/static/js/2.ab48aa38.chunk.js.map
streamlit_cytoscapejs/frontend/build/static/js/main.35eabfb4.chunk.js
streamlit_cytoscapejs/frontend/build/static/js/main.35eabfb4.chunk.js.map
streamlit_cytoscapejs/frontend/build/static/js/runtime-main.64c5e2cb.js
streamlit_cytoscapejs/frontend/build/static/js/runtime-main.64c5e2cb.js.map
streamlit_cytoscapejs-0.0.2.dist-info/LICENSE
streamlit_cytoscapejs-0.0.2.dist-info/METADATA
streamlit_cytoscapejs-0.0.2.dist-info/WHEEL
streamlit_cytoscapejs-0.0.2.dist-info/top_level.txt
streamlit_cytoscapejs-0.0.2.dist-info/RECORD
