Metadata-Version: 2.1
Name: streamlit-cytoscapejs
Version: 0.0.2
Summary: A Streamlit custom component for Cytoscape.js
Home-page: https://github.com/andfanilo/streamlit-cytoscapejs
Author: Fanilo ANDRIANASOLO
Author-email: andfanilo@gmail.com
License: UNKNOWN
Platform: UNKNOWN
Requires-Python: >=3.6
License-File: LICENSE
Requires-Dist: streamlit (>=0.63)
